{"chapter":{"1":{"verse":1,"text":"{Аллилуия.} Хвалите, рабы Господни, хвалите имя Господне."},"2":{"verse":2,"text":"Да будет имя Господне благословенно отныне и вовек."},"3":{"verse":3,"text":"От восхода солнца до запада да будет прославляемо имя Господне."},"4":{"verse":4,"text":"Высок над всеми народами Господь; над небесами слава Его."},"5":{"verse":5,"text":"Кто, как Господь, Бог наш, Который, обитая на высоте,"},"6":{"verse":6,"text":"приклоняется, чтобы призирать на небо и на землю;"},"7":{"verse":7,"text":"из праха поднимает бедного, из брения возвышает нищего,"},"8":{"verse":8,"text":"чтобы посадить его с князьями, с князьями народа его;"},"9":{"verse":9,"text":"неплодную вселяет в дом матерью, радующеюся о детях? Аллилуия!"}},"meta":{"connection":"RSTI","book_number":230,"chapter_number":112,"previous_chapter":{"connection":"RSTI","book_number":230,"chapter":111},"next_chapter":{"connection":"RSTI","book_number":230,"chapter":113}}}