{"chapter":{"1":{"verse":1,"text":[{"name":"pb"},{"name":"word","data":"Περὶ","S":"4012","m":"PREP"},{"name":"word","data":"δὲ","S":"1161","m":"CONJ"},{"name":"word","data":"τῶν","S":"3588","m":"T-GPN"},{"name":"word","data":"πνευματικῶν","S":"4152","m":"A-GPN"},{"name":"punctuation","data":","},{"name":"word","data":"ἀδελφοί","S":"80","m":"N-VPM"},{"name":"punctuation","data":","},{"name":"word","data":"οὐ","S":"3756","m":"PRT-N"},{"name":"word","data":"θέλω","S":"2309","m":"V-PAI-1S"},{"name":"word","data":"ὑμᾶς","S":"4771","m":"P-2AP"},{"name":"word","data":"ἀγνοεῖν","S":"50","m":"V-PAN"},{"name":"punctuation","data":"."}]},"2":{"verse":2,"text":[{"name":"word","data":"οἴδατε","S":"1492","m":"V-RAI-2P"},{"name":"word","data":"ὅτι","S":"3754","m":"CONJ"},{"name":"punctuation","data":","},{"name":"word","data":"ὅτε","S":"3753","m":"ADV"},{"name":"word","data":"ἔθνη","S":"1484","m":"N-NPN"},{"name":"word","data":"ἦτε","S":"1510","m":"V-IAI-2P"},{"name":"punctuation","data":","},{"name":"word","data":"πρὸς","S":"4314","m":"PREP"},{"name":"word","data":"τὰ","S":"3588","m":"T-APN"},{"name":"word","data":"εἴδωλα","S":"1497","m":"N-APN"},{"name":"word","data":"τὰ","S":"3588","m":"T-APN"},{"name":"word","data":"ἄφωνα","S":"880","m":"A-APN"},{"name":"word","data":"ὡς","S":"5613","m":"ADV"},{"name":"word","data":"ἂν","S":"302","m":"PRT"},{"name":"word","data":"ἤγεσθε","S":"71","m":"V-IPI-2P"},{"name":"word","data":"ἀπαγόμενοι","S":"520","m":"V-PPP-NPM"},{"name":"punctuation","data":"."}]},"3":{"verse":3,"text":[{"name":"word","data":"διὸ","S":"1352","m":"CONJ"},{"name":"word","data":"γνωρίζω","S":"1107","m":"V-PAI-1S"},{"name":"word","data":"ὑμῖν","S":"4771","m":"P-2DP"},{"name":"word","data":"ὅτι","S":"3754","m":"CONJ"},{"name":"word","data":"οὐδεὶς","S":"3762","m":"A-NSM-N"},{"name":"word","data":"ἐν","S":"1722","m":"PREP"},{"name":"word","data":"Πνεύματι","S":"4151","m":"N-DSN"},{"name":"word","data":"Θεοῦ","S":"2316","m":"N-GSM"},{"name":"word","data":"λαλῶν","S":"2980","m":"V-PAP-NSM"},{"name":"word","data":"λέγει","S":"3004","m":"V-PAI-3S"},{"name":"word","data":"ἀνάθεμα","S":"331","m":"N-NSN"},{"name":"word","data":"᾽Ιησοῦν","S":"2424","m":"N-ASM"},{"name":"punctuation","data":","},{"name":"word","data":"καὶ","S":"2532","m":"CONJ"},{"name":"word","data":"οὐδεὶς","S":"3762","m":"A-NSM-N"},{"name":"word","data":"δύναται","S":"1410","m":"V-PNI-3S"},{"name":"word","data":"εἰπεῖν","S":"3004","m":"V-2AAN"},{"name":"word","data":"Κύριον","S":"2962","m":"N-ASM"},{"name":"word","data":"᾽Ιησοῦν","S":"2424","m":"N-ASM"},{"name":"word","data":"εἰ","S":"1487","m":"COND"},{"name":"word","data":"μὴ","S":"3361","m":"PRT-N"},{"name":"word","data":"ἐν","S":"1722","m":"PREP"},{"name":"word","data":"Πνεύματι","S":"4151","m":"N-DSN"},{"name":"word","data":"῾Αγίῳ","S":"40","m":"A-DSN"},{"name":"punctuation","data":"."}]},"4":{"verse":4,"text":[{"name":"word","data":"Διαιρέσεις","S":"1243","m":"N-NPF"},{"name":"word","data":"δὲ","S":"1161","m":"CONJ"},{"name":"word","data":"χαρισμάτων","S":"5486","m":"N-GPN"},{"name":"word","data":"εἰσί","S":"1526","m":"V-PAI-3P"},{"name":"punctuation","data":","},{"name":"word","data":"τὸ","S":"3588","m":"T-NSN"},{"name":"word","data":"δὲ","S":"1161","m":"CONJ"},{"name":"word","data":"αὐτὸ","S":"846","m":"P-NSN"},{"name":"word","data":"Πνεῦμα","S":"4151","m":"N-NSN"},{"name":"punctuation","data":"·"}]},"5":{"verse":5,"text":[{"name":"word","data":"καὶ","S":"2532","m":"CONJ"},{"name":"word","data":"διαιρέσεις","S":"1243","m":"N-NPF"},{"name":"word","data":"διακονιῶν","S":"1248","m":"N-GPF"},{"name":"word","data":"εἰσι","S":"1510","m":"V-PAI-3P"},{"name":"punctuation","data":","},{"name":"word","data":"καὶ","S":"2532","m":"CONJ"},{"name":"word","data":"ὁ","S":"3588","m":"T-NSM"},{"name":"word","data":"αὐτὸς","S":"846","m":"P-NSM"},{"name":"word","data":"Κύριος","S":"2962","m":"N-NSM"},{"name":"punctuation","data":"·"}]},"6":{"verse":6,"text":[{"name":"word","data":"καὶ","S":"2532","m":"CONJ"},{"name":"word","data":"διαιρέσεις","S":"1243","m":"N-NPF"},{"name":"word","data":"ἐνεργημάτων","S":"1755","m":"N-GPN"},{"name":"word","data":"εἰσίν","S":"1510","m":"V-PAI-3P"},{"name":"punctuation","data":","},{"name":"word","data":"ὁ","S":"3588","m":"T-NSM"},{"name":"word","data":"δὲ","S":"1161","m":"CONJ"},{"name":"word","data":"αὐτός","S":"846","m":"P-NSM"},{"name":"word","data":"ἐστι","S":"1510","m":"V-PAI-3S"},{"name":"word","data":"Θεός","S":"2316","m":"N-NSM"},{"name":"punctuation","data":","},{"name":"word","data":"ὁ","S":"3588","m":"T-NSM"},{"name":"word","data":"ἐνεργῶν","S":"1754","m":"V-PAP-NSM"},{"name":"word","data":"τὰ","S":"3588","m":"T-APN"},{"name":"word","data":"πάντα","S":"3956","m":"A-APN"},{"name":"word","data":"ἐν","S":"1722","m":"PREP"},{"name":"word","data":"πᾶσιν","S":"3956","m":"A-DPM"},{"name":"punctuation","data":"."}]},"7":{"verse":7,"text":[{"name":"word","data":"῾Εκάστῳ","S":"1538","m":"A-DSM"},{"name":"word","data":"δὲ","S":"1161","m":"CONJ"},{"name":"word","data":"δίδοται","S":"1325","m":"V-PPI-3S"},{"name":"word","data":"ἡ","S":"3588","m":"T-NSF"},{"name":"word","data":"φανέρωσις","S":"5321","m":"N-NSF"},{"name":"word","data":"τοῦ","S":"3588","m":"T-GSN"},{"name":"word","data":"Πνεύματος","S":"4151","m":"N-GSN"},{"name":"word","data":"πρὸς","S":"4314","m":"PREP"},{"name":"word","data":"τὸ","S":"3588","m":"T-ASN"},{"name":"word","data":"συμφέρον","S":"4851","m":"V-PAP-ASN"},{"name":"punctuation","data":"."}]},"8":{"verse":8,"text":[{"name":"word","data":"ᾧ","S":"3739","m":"R-DSM"},{"name":"word","data":"μὲν","S":"3303","m":"PRT"},{"name":"word","data":"γὰρ","S":"1063","m":"CONJ"},{"name":"word","data":"διὰ","S":"1223","m":"PREP"},{"name":"word","data":"τοῦ","S":"3588","m":"T-GSN"},{"name":"word","data":"Πνεύματος","S":"4151","m":"N-GSN"},{"name":"word","data":"δίδοται","S":"1325","m":"V-PPI-3S"},{"name":"word","data":"λόγος","S":"3056","m":"N-NSM"},{"name":"word","data":"σοφίας","S":"4678","m":"N-GSF"},{"name":"punctuation","data":","},{"name":"word","data":"ἄλλῳ","S":"243","m":"A-DSM"},{"name":"word","data":"δὲ","S":"1161","m":"CONJ"},{"name":"word","data":"λόγος","S":"3056","m":"N-NSM"},{"name":"word","data":"γνώσεως","S":"1108","m":"N-GSF"},{"name":"word","data":"κατὰ","S":"2596","m":"PREP"},{"name":"word","data":"τὸ","S":"3588","m":"T-ASN"},{"name":"word","data":"αὐτὸ","S":"846","m":"P-ASN"},{"name":"word","data":"Πνεῦμα","S":"4151","m":"N-ASN"},{"name":"punctuation","data":","}]},"9":{"verse":9,"text":[{"name":"word","data":"ἑτέρῳ","S":"2087","m":"A-DSM"},{"name":"word","data":"δὲ","S":"1161","m":"CONJ"},{"name":"word","data":"πίστις","S":"4102","m":"N-NSF"},{"name":"word","data":"ἐν","S":"1722","m":"PREP"},{"name":"word","data":"τῷ","S":"3588","m":"T-DSN"},{"name":"word","data":"αὐτῷ","S":"846","m":"P-DSN"},{"name":"word","data":"Πνεύματι","S":"4151","m":"N-DSN"},{"name":"punctuation","data":","},{"name":"word","data":"ἄλλῳ","S":"243","m":"A-DSM"},{"name":"word","data":"δὲ","S":"1161","m":"CONJ"},{"name":"word","data":"χαρίσματα","S":"5486","m":"N-NPN"},{"name":"word","data":"ἰαμάτων","S":"2386","m":"N-GPN"},{"name":"word","data":"ἐν","S":"1722","m":"PREP"},{"name":"word","data":"τῷ","S":"3588","m":"T-DSN"},{"name":"word","data":"αὐτῷ","S":"846","m":"P-DSN"},{"name":"word","data":"Πνεύματι","S":"4151","m":"N-DSN"},{"name":"punctuation","data":","}]},"10":{"verse":10,"text":[{"name":"word","data":"ἄλλῳ","S":"243","m":"A-DSM"},{"name":"word","data":"δὲ","S":"1161","m":"CONJ"},{"name":"word","data":"ἐνεργήματα","S":"1755","m":"N-NPN"},{"name":"word","data":"δυνάμεων","S":"1411","m":"N-GPF"},{"name":"punctuation","data":","},{"name":"word","data":"ἄλλῳ","S":"243","m":"A-DSM"},{"name":"word","data":"δὲ","S":"1161","m":"CONJ"},{"name":"word","data":"προφητεία","S":"4394","m":"N-NSF"},{"name":"punctuation","data":","},{"name":"word","data":"ἄλλῳ","S":"243","m":"A-DSM"},{"name":"word","data":"δὲ","S":"1161","m":"CONJ"},{"name":"word","data":"διακρίσεις","S":"1253","m":"N-NPF"},{"name":"word","data":"πνευμάτων","S":"4151","m":"N-GPN"},{"name":"punctuation","data":","},{"name":"word","data":"ἑτέρῳ","S":"2087","m":"A-DSM"},{"name":"word","data":"δὲ","S":"1161","m":"CONJ"},{"name":"word","data":"γένη","S":"1085","m":"N-NPN"},{"name":"word","data":"γλωσσῶν","S":"1100","m":"N-GPF"},{"name":"punctuation","data":","},{"name":"word","data":"ἄλλῳ","S":"243","m":"A-DSM"},{"name":"word","data":"δὲ","S":"1161","m":"CONJ"},{"name":"word","data":"ἑρμηνεία","S":"2058","m":"N-NSF"},{"name":"word","data":"γλωσσῶν","S":"1100","m":"N-GPF"},{"name":"punctuation","data":"·"}]},"11":{"verse":11,"text":[{"name":"word","data":"πάντα","S":"3956","m":"A-APN"},{"name":"word","data":"δὲ","S":"1161","m":"CONJ"},{"name":"word","data":"ταῦτα","S":"3778","m":"D-APN"},{"name":"word","data":"ἐνεργεῖ","S":"1754","m":"V-PAI-3S"},{"name":"word","data":"τὸ","S":"3588","m":"T-NSN"},{"name":"word","data":"ἓν","S":"1520","m":"A-NSN"},{"name":"word","data":"καὶ","S":"2532","m":"CONJ"},{"name":"word","data":"τὸ","S":"3588","m":"T-NSN"},{"name":"word","data":"αὐτὸ","S":"846","m":"P-NSN"},{"name":"word","data":"Πνεῦμα","S":"4151","m":"N-NSN"},{"name":"punctuation","data":","},{"name":"word","data":"διαιροῦν","S":"1244","m":"V-PAP-NSN"},{"name":"word","data":"ἰδίᾳ","S":"2398","m":"A-DSF"},{"name":"word","data":"ἑκάστῳ","S":"1538","m":"A-DSM"},{"name":"word","data":"καθὼς","S":"2531","m":"ADV"},{"name":"word","data":"βούλεται","S":"1014","m":"V-PNI-3S"},{"name":"punctuation","data":"."}]},"12":{"verse":12,"text":[{"name":"pb"},{"name":"word","data":"Καθάπερ","S":"2509","m":"ADV"},{"name":"word","data":"γὰρ","S":"1063","m":"CONJ"},{"name":"word","data":"τὸ","S":"3588","m":"T-NSN"},{"name":"word","data":"σῶμα","S":"4983","m":"N-NSN"},{"name":"word","data":"ἕν","S":"1520","m":"A-NSN"},{"name":"word","data":"ἐστι","S":"1510","m":"V-PAI-3S"},{"name":"word","data":"καὶ","S":"2532","m":"CONJ"},{"name":"word","data":"μέλη","S":"3196","m":"N-APN"},{"name":"word","data":"ἔχει","S":"2192","m":"V-PAI-3S"},{"name":"word","data":"πολλά","S":"4183","m":"A-APN"},{"name":"punctuation","data":","},{"name":"word","data":"πάντα","S":"3956","m":"A-NPN"},{"name":"word","data":"δὲ","S":"1161","m":"CONJ"},{"name":"word","data":"τὰ","S":"3588","m":"T-NPN"},{"name":"word","data":"μέλη","S":"3196","m":"N-NPN"},{"name":"word","data":"τοῦ","S":"3588","m":"T-GSN"},{"name":"word","data":"σώματος","S":"4983","m":"N-GSN"},{"name":"word","data":"τοῦ","S":"3588","m":"T-GSN"},{"name":"word","data":"ἑνός","S":"1520","m":"A-GSN"},{"name":"punctuation","data":","},{"name":"word","data":"πολλὰ","S":"4183","m":"A-NPN"},{"name":"word","data":"ὄντα","S":"1510","m":"V-PAP-NPN"},{"name":"punctuation","data":","},{"name":"word","data":"ἕν","S":"1520","m":"A-NSN"},{"name":"word","data":"ἐστι","S":"1510","m":"V-PAI-3S"},{"name":"word","data":"σῶμα","S":"4983","m":"N-NSN"},{"name":"punctuation","data":","},{"name":"word","data":"οὕτω","S":"3779","m":"ADV"},{"name":"word","data":"καὶ","S":"2532","m":"CONJ"},{"name":"word","data":"ὁ","S":"3588","m":"T-NSM"},{"name":"word","data":"Χριστός","S":"5547","m":"N-NSM"},{"name":"punctuation","data":"·"}]},"13":{"verse":13,"text":[{"name":"word","data":"καὶ","S":"2532","m":"CONJ"},{"name":"word","data":"γὰρ","S":"1063","m":"CONJ"},{"name":"word","data":"ἐν","S":"1722","m":"PREP"},{"name":"word","data":"ἑνὶ","S":"1520","m":"A-DSN"},{"name":"word","data":"Πνεύματι","S":"4151","m":"N-DSN"},{"name":"word","data":"ἡμεῖς","S":"1473","m":"P-1NP"},{"name":"word","data":"πάντες","S":"3956","m":"A-NPM"},{"name":"word","data":"εἰς","S":"1519","m":"PREP"},{"name":"word","data":"ἓν","S":"1520","m":"A-ASN"},{"name":"word","data":"σῶμα","S":"4983","m":"N-ASN"},{"name":"word","data":"ἐβαπτίσθημεν","S":"907","m":"V-API-1P"},{"name":"punctuation","data":","},{"name":"word","data":"εἴτε","S":"1535","m":"CONJ"},{"name":"word","data":"᾽Ιουδαῖοι","S":"2453","m":"A-NPM"},{"name":"word","data":"εἴτε","S":"1535","m":"CONJ"},{"name":"word","data":"῞Ελληνες","S":"1672","m":"N-NPM"},{"name":"punctuation","data":","},{"name":"word","data":"εἴτε","S":"1535","m":"CONJ"},{"name":"word","data":"δοῦλοι","S":"1401","m":"N-NPM"},{"name":"word","data":"εἴτε","S":"1535","m":"CONJ"},{"name":"word","data":"ἐλεύθεροι","S":"1658","m":"A-NPM"},{"name":"punctuation","data":","},{"name":"word","data":"καὶ","S":"2532","m":"CONJ"},{"name":"word","data":"πάντες","S":"3956","m":"A-NPM"},{"name":"word","data":"εἰς","S":"1519","m":"PREP"},{"name":"word","data":"ἓν","S":"1520","m":"A-ASN"},{"name":"word","data":"Πνεῦμα","S":"4151","m":"N-ASN"},{"name":"word","data":"ἐποτίσθημεν","S":"4222","m":"V-API-1P"},{"name":"punctuation","data":"."}]},"14":{"verse":14,"text":[{"name":"word","data":"καὶ","S":"2532","m":"CONJ"},{"name":"word","data":"γὰρ","S":"1063","m":"CONJ"},{"name":"word","data":"τὸ","S":"3588","m":"T-NSN"},{"name":"word","data":"σῶμα","S":"4983","m":"N-NSN"},{"name":"word","data":"οὐκ","S":"3756","m":"PRT-N"},{"name":"word","data":"ἔστιν","S":"1510","m":"V-PAI-3S"},{"name":"word","data":"ἓν","S":"1520","m":"A-NSN"},{"name":"word","data":"μέλος","S":"3196","m":"N-NSN"},{"name":"punctuation","data":","},{"name":"word","data":"ἀλλὰ","S":"235","m":"CONJ"},{"name":"word","data":"πολλά","S":"4183","m":"A-NPN"},{"name":"punctuation","data":"."}]},"15":{"verse":15,"text":[{"name":"word","data":"ἐὰν","S":"1437","m":"COND"},{"name":"word","data":"εἴπῃ","S":"3004","m":"V-2AAS-3S"},{"name":"word","data":"ὁ","S":"3588","m":"T-NSM"},{"name":"word","data":"πούς","S":"4228","m":"N-NSM"},{"name":"punctuation","data":","},{"name":"word","data":"ὅτι","S":"3754","m":"CONJ"},{"name":"word","data":"οὐκ","S":"3756","m":"PRT-N"},{"name":"word","data":"εἰμὶ","S":"1510","m":"V-PAI-1S"},{"name":"word","data":"χείρ","S":"5495","m":"N-NSF"},{"name":"punctuation","data":","},{"name":"word","data":"οὐκ","S":"3756","m":"PRT-N"},{"name":"word","data":"εἰμὶ","S":"1510","m":"V-PAI-1S"},{"name":"word","data":"ἐκ","S":"1537","m":"PREP"},{"name":"word","data":"τοῦ","S":"3588","m":"T-GSN"},{"name":"word","data":"σώματος","S":"4983","m":"N-GSN"},{"name":"punctuation","data":","},{"name":"dash"},{"name":"word","data":"οὐ","S":"3756","m":"PRT-N"},{"name":"word","data":"παρὰ","S":"3844","m":"PREP"},{"name":"word","data":"τοῦτο","S":"3778","m":"D-ASN"},{"name":"word","data":"οὐκ","S":"3756","m":"PRT-N"},{"name":"word","data":"ἔστιν","S":"1510","m":"V-PAI-3S"},{"name":"word","data":"ἐκ","S":"1537","m":"PREP"},{"name":"word","data":"τοῦ","S":"3588","m":"T-GSN"},{"name":"word","data":"σώματος","S":"4983","m":"N-GSN"},{"name":"punctuation","data":";"}]},"16":{"verse":16,"text":[{"name":"word","data":"καὶ","S":"2532","m":"CONJ"},{"name":"word","data":"ἐὰν","S":"1437","m":"COND"},{"name":"word","data":"εἴπῃ","S":"3004","m":"V-2AAS-3S"},{"name":"word","data":"τὸ","S":"3588","m":"T-NSN"},{"name":"word","data":"οὖς","S":"3775","m":"N-NSN"},{"name":"punctuation","data":","},{"name":"word","data":"ὅτι","S":"3754","m":"CONJ"},{"name":"word","data":"οὐκ","S":"3756","m":"PRT-N"},{"name":"word","data":"εἰμὶ","S":"1510","m":"V-PAI-1S"},{"name":"word","data":"ὀφθαλμός","S":"3788","m":"N-NSM"},{"name":"punctuation","data":","},{"name":"word","data":"οὐκ","S":"3756","m":"PRT-N"},{"name":"word","data":"εἰμὶ","S":"1510","m":"V-PAI-1S"},{"name":"word","data":"ἐκ","S":"1537","m":"PREP"},{"name":"word","data":"τοῦ","S":"3588","m":"T-GSN"},{"name":"word","data":"σώματος","S":"4983","m":"N-GSN"},{"name":"punctuation","data":","},{"name":"dash"},{"name":"word","data":"οὐ","S":"3756","m":"PRT-N"},{"name":"word","data":"παρὰ","S":"3844","m":"PREP"},{"name":"word","data":"τοῦτο","S":"3778","m":"D-ASN"},{"name":"word","data":"οὐκ","S":"3756","m":"PRT-N"},{"name":"word","data":"ἔστιν","S":"1510","m":"V-PAI-3S"},{"name":"word","data":"ἐκ","S":"1537","m":"PREP"},{"name":"word","data":"τοῦ","S":"3588","m":"T-GSN"},{"name":"word","data":"σώματος","S":"4983","m":"N-GSN"},{"name":"punctuation","data":";"}]},"17":{"verse":17,"text":[{"name":"word","data":"εἰ","S":"1487","m":"COND"},{"name":"word","data":"ὅλον","S":"3650","m":"A-NSN"},{"name":"word","data":"τὸ","S":"3588","m":"T-NSN"},{"name":"word","data":"σῶμα","S":"4983","m":"N-NSN"},{"name":"word","data":"ὀφθαλμός","S":"3788","m":"N-NSM"},{"name":"punctuation","data":","},{"name":"word","data":"ποῦ","S":"4226","m":"ADV-I"},{"name":"word","data":"ἡ","S":"3588","m":"T-NSF"},{"name":"word","data":"ἀκοή","S":"189","m":"N-NSF"},{"name":"punctuation","data":";"},{"name":"word","data":"εἰ","S":"1487","m":"COND"},{"name":"word","data":"ὅλον","S":"3650","m":"A-NSN"},{"name":"word","data":"ἀκοή","S":"189","m":"N-NSF"},{"name":"punctuation","data":","},{"name":"word","data":"ποῦ","S":"4226","m":"ADV-I"},{"name":"word","data":"ἡ","S":"3588","m":"T-NSF"},{"name":"word","data":"ὄσφρησις","S":"3750","m":"N-NSF"},{"name":"punctuation","data":";"}]},"18":{"verse":18,"text":[{"name":"word","data":"νυνὶ","S":"3570","m":"ADV"},{"name":"word","data":"δὲ","S":"1161","m":"CONJ"},{"name":"word","data":"ὁ","S":"3588","m":"T-NSM"},{"name":"word","data":"Θεὸς","S":"2316","m":"N-NSM"},{"name":"word","data":"ἔθετο","S":"5087","m":"V-2AMI-3S"},{"name":"word","data":"τὰ","S":"3588","m":"T-APN"},{"name":"word","data":"μέλη","S":"3196","m":"N-APN"},{"name":"word","data":"ἓν","S":"1520","m":"A-ASN"},{"name":"word","data":"ἕκαστον","S":"1538","m":"A-ASN"},{"name":"word","data":"αὐτῶν","S":"846","m":"P-GPN"},{"name":"word","data":"ἐν","S":"1722","m":"PREP"},{"name":"word","data":"τῷ","S":"3588","m":"T-DSN"},{"name":"word","data":"σώματι","S":"4983","m":"N-DSN"},{"name":"word","data":"καθὼς","S":"2531","m":"ADV"},{"name":"word","data":"ἠθέλησεν","S":"2309","m":"V-AAI-3S"},{"name":"punctuation","data":"."}]},"19":{"verse":19,"text":[{"name":"word","data":"εἰ","S":"1487","m":"COND"},{"name":"word","data":"δὲ","S":"1161","m":"CONJ"},{"name":"word","data":"ἦν","S":"1510","m":"V-IAI-3S"},{"name":"word","data":"τὰ","S":"3588","m":"T-NPN"},{"name":"word","data":"πάντα","S":"3956","m":"A-NPN"},{"name":"word","data":"ἓν","S":"1520","m":"A-NSN"},{"name":"word","data":"μέλος","S":"3196","m":"N-NSN"},{"name":"punctuation","data":","},{"name":"word","data":"ποῦ","S":"4226","m":"ADV-I"},{"name":"word","data":"τὸ","S":"3588","m":"T-NSN"},{"name":"word","data":"σῶμα","S":"4983","m":"N-NSN"},{"name":"punctuation","data":";"}]},"20":{"verse":20,"text":[{"name":"word","data":"νῦν","S":"3568","m":"ADV"},{"name":"word","data":"δὲ","S":"1161","m":"CONJ"},{"name":"word","data":"πολλὰ","S":"4183","m":"A-NPN"},{"name":"word","data":"μὲν","S":"3303","m":"PRT"},{"name":"word","data":"μέλη","S":"3196","m":"N-NPN"},{"name":"punctuation","data":","},{"name":"word","data":"ἓν","S":"1520","m":"A-NSN"},{"name":"word","data":"δὲ","S":"1161","m":"CONJ"},{"name":"word","data":"σῶμα","S":"4983","m":"N-NSN"},{"name":"punctuation","data":"."}]},"21":{"verse":21,"text":[{"name":"word","data":"οὐ","S":"3756","m":"PRT-N"},{"name":"word","data":"δύναται","S":"1410","m":"V-PNI-3S"},{"name":"word","data":"δὲ","S":"1161","m":"CONJ"},{"name":"word","data":"ὀφθαλμὸς","S":"3788","m":"N-NSM"},{"name":"word","data":"εἰπεῖν","S":"3004","m":"V-2AAN"},{"name":"word","data":"τῇ","S":"3588","m":"T-DSF"},{"name":"word","data":"χειρί","S":"5495","m":"N-DSF"},{"name":"punctuation","data":"·"},{"name":"word","data":"χρείαν","S":"5532","m":"N-ASF"},{"name":"word","data":"σου","S":"4771","m":"P-2GS"},{"name":"word","data":"οὐκ","S":"3756","m":"PRT-N"},{"name":"word","data":"ἔχω","S":"2192","m":"V-PAI-1S"},{"name":"punctuation","data":"·"},{"name":"word","data":"ἢ","S":"2228","m":"PRT"},{"name":"word","data":"πάλιν","S":"3825","m":"ADV"},{"name":"word","data":"ἡ","S":"3588","m":"T-NSF"},{"name":"word","data":"κεφαλὴ","S":"2776","m":"N-NSF"},{"name":"word","data":"τοῖς","S":"3588","m":"T-DPM"},{"name":"word","data":"ποσί","S":"4228","m":"N-DPM"},{"name":"punctuation","data":"·"},{"name":"word","data":"χρείαν","S":"5532","m":"N-ASF"},{"name":"word","data":"ὑμῶν","S":"4771","m":"P-2GP"},{"name":"word","data":"οὐκ","S":"3756","m":"PRT-N"},{"name":"word","data":"ἔχω","S":"2192","m":"V-PAI-1S"},{"name":"punctuation","data":"·"}]},"22":{"verse":22,"text":[{"name":"word","data":"ἀλλὰ","S":"235","m":"CONJ"},{"name":"word","data":"πολλῷ","S":"4183","m":"A-DSN"},{"name":"word","data":"μᾶλλον","S":"3123","m":"ADV"},{"name":"word","data":"τὰ","S":"3588","m":"T-NPN"},{"name":"word","data":"δοκοῦντα","S":"1380","m":"V-PAP-NPN"},{"name":"word","data":"μέλη","S":"3196","m":"N-NPN"},{"name":"word","data":"τοῦ","S":"3588","m":"T-GSN"},{"name":"word","data":"σώματος","S":"4983","m":"N-GSN"},{"name":"word","data":"ἀσθενέστερα","S":"772","m":"A-NPN-C"},{"name":"word","data":"ὑπάρχειν","S":"5225","m":"V-PAN"},{"name":"word","data":"ἀναγκαῖά","S":"316","m":"A-NPN"},{"name":"word","data":"ἐστι","S":"1510","m":"V-PAI-3S"},{"name":"punctuation","data":","}]},"23":{"verse":23,"text":[{"name":"word","data":"καὶ","S":"2532","m":"CONJ"},{"name":"word","data":"ἃ","S":"3739","m":"R-APN"},{"name":"word","data":"δοκοῦμεν","S":"1380","m":"V-PAI-1P"},{"name":"word","data":"ἀτιμότερα","S":"820","m":"A-APN-C"},{"name":"word","data":"εἶναι","S":"1510","m":"V-PAN"},{"name":"word","data":"τοῦ","S":"3588","m":"T-GSN"},{"name":"word","data":"σώματος","S":"4983","m":"N-GSN"},{"name":"punctuation","data":","},{"name":"word","data":"τούτοις","S":"3778","m":"D-DPN"},{"name":"word","data":"τιμὴν","S":"5092","m":"N-ASF"},{"name":"word","data":"περισσοτέραν","S":"4053","m":"A-ASF-C"},{"name":"word","data":"περιτίθεμεν","S":"4060","m":"V-PAI-1P"},{"name":"punctuation","data":","},{"name":"word","data":"καὶ","S":"2532","m":"CONJ"},{"name":"word","data":"τὰ","S":"3588","m":"T-NPN"},{"name":"word","data":"ἀσχήμονα","S":"809","m":"A-NPN"},{"name":"word","data":"ἡμῶν","S":"1473","m":"P-1GP"},{"name":"word","data":"εὐσχημοσύνην","S":"2157","m":"N-ASF"},{"name":"word","data":"περισσοτέραν","S":"4053","m":"A-ASF-C"},{"name":"word","data":"ἔχει","S":"2192","m":"V-PAI-3S"},{"name":"punctuation","data":","}]},"24":{"verse":24,"text":[{"name":"word","data":"τὰ","S":"3588","m":"T-NPN"},{"name":"word","data":"δὲ","S":"1161","m":"CONJ"},{"name":"word","data":"εὐσχήμονα","S":"2158","m":"A-NPN"},{"name":"word","data":"ἡμῶν","S":"1473","m":"P-1GP"},{"name":"word","data":"οὐ","S":"3756","m":"PRT-N"},{"name":"word","data":"χρείαν","S":"5532","m":"N-ASF"},{"name":"word","data":"ἔχει","S":"2192","m":"V-PAI-3S"},{"name":"punctuation","data":"."},{"name":"word","data":"ἀλλ᾽","S":"235","m":"CONJ"},{"name":"word","data":"ὁ","S":"3588","m":"T-NSM"},{"name":"word","data":"Θεὸς","S":"2316","m":"N-NSM"},{"name":"word","data":"συνεκέρασε","S":"4786","m":"V-AAI-3S"},{"name":"word","data":"τὸ","S":"3588","m":"T-ASN"},{"name":"word","data":"σῶμα","S":"4983","m":"N-ASN"},{"name":"punctuation","data":","},{"name":"word","data":"τῷ","S":"3588","m":"T-DSN"},{"name":"word","data":"ὑστεροῦντι","S":"5302","m":"V-PAP-DSN"},{"name":"word","data":"περισσοτέραν","S":"4053","m":"A-ASF-C"},{"name":"word","data":"δοὺς","S":"1325","m":"V-2AAP-NSM"},{"name":"word","data":"τιμήν","S":"5092","m":"N-ASF"},{"name":"punctuation","data":","}]},"25":{"verse":25,"text":[{"name":"word","data":"ἵνα","S":"2443","m":"CONJ"},{"name":"word","data":"μὴ","S":"3361","m":"PRT-N"},{"name":"word","data":"ᾖ","S":"1510","m":"V-PAS-3S"},{"name":"word","data":"σχίσμα","S":"4978","m":"N-NSN"},{"name":"word","data":"ἐν","S":"1722","m":"PREP"},{"name":"word","data":"τῷ","S":"3588","m":"T-DSN"},{"name":"word","data":"σώματι","S":"4983","m":"N-DSN"},{"name":"punctuation","data":","},{"name":"word","data":"ἀλλὰ","S":"235","m":"CONJ"},{"name":"word","data":"τὸ","S":"3588","m":"T-ASN"},{"name":"word","data":"αὐτὸ","S":"846","m":"P-ASN"},{"name":"word","data":"ὑπὲρ","S":"5228","m":"PREP"},{"name":"word","data":"ἀλλήλων","S":"240","m":"C-GPN"},{"name":"word","data":"μεριμνῶσι","S":"3309","m":"V-PAS-3P"},{"name":"word","data":"τὰ","S":"3588","m":"T-NPN"},{"name":"word","data":"μέλη","S":"3196","m":"N-NPN"},{"name":"punctuation","data":"·"}]},"26":{"verse":26,"text":[{"name":"word","data":"καὶ","S":"2532","m":"CONJ"},{"name":"word","data":"εἴτε","S":"1535","m":"CONJ"},{"name":"word","data":"πάσχει","S":"3958","m":"V-PAI-3S"},{"name":"word","data":"ἓν","S":"1520","m":"A-NSN"},{"name":"word","data":"μέλος","S":"3196","m":"N-NSN"},{"name":"punctuation","data":","},{"name":"word","data":"συμπάσχει","S":"4841","m":"V-PAI-3S"},{"name":"word","data":"πάντα","S":"3956","m":"A-NPN"},{"name":"word","data":"τὰ","S":"3588","m":"T-NPN"},{"name":"word","data":"μέλη","S":"3196","m":"N-NPN"},{"name":"punctuation","data":","},{"name":"word","data":"εἴτε","S":"1535","m":"CONJ"},{"name":"word","data":"δοξάζεται","S":"1392","m":"V-PPI-3S"},{"name":"word","data":"ἓν","S":"1520","m":"A-NSN"},{"name":"word","data":"μέλος","S":"3196","m":"N-NSN"},{"name":"punctuation","data":","},{"name":"word","data":"συγχαίρει","S":"4796","m":"V-PAI-3S"},{"name":"word","data":"πάντα","S":"3956","m":"A-NPN"},{"name":"word","data":"τὰ","S":"3588","m":"T-NPN"},{"name":"word","data":"μέλη","S":"3196","m":"N-NPN"},{"name":"punctuation","data":"."}]},"27":{"verse":27,"text":[{"name":"word","data":"῾Υμεῖς","S":"4771","m":"P-2NP"},{"name":"word","data":"δέ","S":"1161","m":"CONJ"},{"name":"word","data":"ἐστε","S":"1510","m":"V-PAI-2P"},{"name":"word","data":"σῶμα","S":"4983","m":"N-NSN"},{"name":"word","data":"Χριστοῦ","S":"5547","m":"N-GSM"},{"name":"word","data":"καὶ","S":"2532","m":"CONJ"},{"name":"word","data":"μέλη","S":"3196","m":"N-NPN"},{"name":"word","data":"ἐκ","S":"1537","m":"PREP"},{"name":"word","data":"μέρους","S":"3313","m":"N-GSN"},{"name":"punctuation","data":"."}]},"28":{"verse":28,"text":[{"name":"pb"},{"name":"word","data":"Καὶ","S":"2532","m":"CONJ"},{"name":"word","data":"οὓς","S":"3739","m":"R-APM"},{"name":"word","data":"μὲν","S":"3303","m":"PRT"},{"name":"word","data":"ἔθετο","S":"5087","m":"V-2AMI-3S"},{"name":"word","data":"ὁ","S":"3588","m":"T-NSM"},{"name":"word","data":"Θεὸς","S":"2316","m":"N-NSM"},{"name":"word","data":"ἐν","S":"1722","m":"PREP"},{"name":"word","data":"τῇ","S":"3588","m":"T-DSF"},{"name":"word","data":"ἐκκλησίᾳ","S":"1577","m":"N-DSF"},{"name":"word","data":"πρῶτον","S":"4412","m":"ADV-S"},{"name":"word","data":"ἀποστόλους","S":"652","m":"N-APM"},{"name":"punctuation","data":","},{"name":"word","data":"δεύτερον","S":"1208","m":"ADV"},{"name":"word","data":"προφήτας","S":"4396","m":"N-APM"},{"name":"punctuation","data":","},{"name":"word","data":"τρίτον","S":"5154","m":"ADV"},{"name":"word","data":"διδασκάλους","S":"1320","m":"N-APM"},{"name":"punctuation","data":","},{"name":"word","data":"ἔπειτα","S":"1899","m":"ADV"},{"name":"word","data":"δυνάμεις","S":"1411","m":"N-APF"},{"name":"punctuation","data":","},{"name":"word","data":"εἶτα","S":"1534","m":"ADV"},{"name":"word","data":"χαρίσματα","S":"5486","m":"N-APN"},{"name":"word","data":"ἰαμάτων","S":"2386","m":"N-GPN"},{"name":"punctuation","data":","},{"name":"word","data":"ἀντιλήψεις","S":"484","m":"N-APF"},{"name":"punctuation","data":","},{"name":"word","data":"κυβερνήσεις","S":"2941","m":"N-APF"},{"name":"punctuation","data":","},{"name":"word","data":"γένη","S":"1085","m":"N-APN"},{"name":"word","data":"γλωσσῶν","S":"1100","m":"N-GPF"},{"name":"punctuation","data":"."}]},"29":{"verse":29,"text":[{"name":"word","data":"μὴ","S":"3361","m":"PRT-N"},{"name":"word","data":"πάντες","S":"3956","m":"A-NPM"},{"name":"word","data":"ἀπόστολοι","S":"652","m":"N-NPM"},{"name":"punctuation","data":";"},{"name":"word","data":"μὴ","S":"3361","m":"PRT-N"},{"name":"word","data":"πάντες","S":"3956","m":"A-NPM"},{"name":"word","data":"προφῆται","S":"4396","m":"N-NPM"},{"name":"punctuation","data":";"},{"name":"word","data":"μὴ","S":"3361","m":"PRT-N"},{"name":"word","data":"πάντες","S":"3956","m":"A-NPM"},{"name":"word","data":"διδάσκαλοι","S":"1320","m":"N-NPM"},{"name":"punctuation","data":";"},{"name":"word","data":"μὴ","S":"3361","m":"PRT-N"},{"name":"word","data":"πάντες","S":"3956","m":"A-NPM"},{"name":"word","data":"δυνάμεις","S":"1411","m":"N-NPF"},{"name":"punctuation","data":";"}]},"30":{"verse":30,"text":[{"name":"word","data":"μὴ","S":"3361","m":"PRT-N"},{"name":"word","data":"πάντες","S":"3956","m":"A-NPM"},{"name":"word","data":"χαρίσματα","S":"5486","m":"N-APN"},{"name":"word","data":"ἔχουσιν","S":"2192","m":"V-PAI-3P"},{"name":"word","data":"ἰαμάτων","S":"2386","m":"N-GPN"},{"name":"punctuation","data":";"},{"name":"word","data":"μὴ","S":"3361","m":"PRT-N"},{"name":"word","data":"πάντες","S":"3956","m":"A-NPM"},{"name":"word","data":"γλώσσαις","S":"1100","m":"N-DPF"},{"name":"word","data":"λαλοῦσι","S":"2980","m":"V-PAI-3P"},{"name":"punctuation","data":";"},{"name":"word","data":"μὴ","S":"3361","m":"PRT-N"},{"name":"word","data":"πάντες","S":"3956","m":"A-NPM"},{"name":"word","data":"διερμηνεύουσι","S":"1329","m":"V-PAI-3P"},{"name":"punctuation","data":";"}]},"31":{"verse":31,"text":[{"name":"word","data":"ζηλοῦτε","S":"2206","m":"V-PAM-2P"},{"name":"word","data":"δὲ","S":"1161","m":"CONJ"},{"name":"word","data":"τὰ","S":"3588","m":"T-APN"},{"name":"word","data":"χαρίσματα","S":"5486","m":"N-APN"},{"name":"word","data":"τὰ","S":"3588","m":"T-APN"},{"name":"word","data":"κρείττονα","S":"2909","m":"A-APN-C"},{"name":"punctuation","data":"."},{"name":"word","data":"καὶ","S":"2532","m":"CONJ"},{"name":"word","data":"ἔτι","S":"2089","m":"ADV"},{"name":"word","data":"καθ᾽","S":"2596","m":"PREP"},{"name":"word","data":"ὑπερβολὴν","S":"5236","m":"N-ASF"},{"name":"word","data":"ὁδὸν","S":"3598","m":"N-ASF"},{"name":"word","data":"ὑμῖν","S":"4771","m":"P-2DP"},{"name":"word","data":"δείκνυμι","S":"1166","m":"V-PAI-1S"},{"name":"punctuation","data":"."}]}},"meta":{"connection":"NTPT+","book_number":530,"chapter_number":12,"previous_chapter":{"connection":"NTPT+","book_number":530,"chapter":11},"next_chapter":{"connection":"NTPT+","book_number":530,"chapter":13}}}